MANIFEST.in
README.md
setup.cfg
setup.py
TableMongo/__init__.py
TableMongo/key.py
TableMongo/model.py
TableMongo/properties.py
TableMongo/query.py
TableMongo.egg-info/PKG-INFO
TableMongo.egg-info/SOURCES.txt
TableMongo.egg-info/dependency_links.txt
TableMongo.egg-info/requires.txt
TableMongo.egg-info/top_level.txt
TableMongo/inspector/__init__.py
tests/deployment.py
tests/models.py
tests/playground.py