Metadata-Version: 1.1
Name: TableMongo
Version: 1.0.2
Summary: TableMongo. A MongoDB ORM based on Google's BigTable Syntax
Home-page: https://github.com/HunterLarco/TableMongo
Author: Hunter John Larco
Author-email: hunter@larcolabs.com
License: MIT
Keywords: mongodb tablemongo table mongo db database storage orm
Platform: UNKNOWN
Classifier: Development Status :: 2 - Pre-Alpha
Classifier: Intended Audience :: Developers
Classifier: Topic :: Software Development :: Libraries :: Python Modules
Classifier: License :: OSI Approved :: MIT License
Classifier: Programming Language :: Python :: 2
Classifier: Programming Language :: Python :: 2.6
Classifier: Programming Language :: Python :: 2.7
Classifier: Programming Language :: Python :: 3
Classifier: Programming Language :: Python :: 3.2
Classifier: Programming Language :: Python :: 3.3
Classifier: Programming Language :: Python :: 3.4
